[
  {
    "first-impression-image": "feature-img/banner-image-1.jpg",
    "first-impression-caption": "Banner Image 1",
    "first-impression-order": 1
  },
  {
    "first-impression-image": "feature-img/banner-image-2.jpg",
    "first-impression-caption": "Banner Image 2",
    "first-impression-order": 2
  },
  {
    "first-impression-image": "feature-img/banner-image-3.jpg",
    "first-impression-caption": "Banner Image 3",
    "first-impression-order": 3
  },
  {
    "first-impression-image": "feature-img/banner-image-4.jpg",
    "first-impression-caption": "Banner Image 4",
    "first-impression-order": 4
  },
  {
    "first-impression-image": "feature-img/banner-image-5.jpg",
    "first-impression-caption": "Banner Image 5",
    "first-impression-order": 5
  },
  {
    "first-impression-image": "feature-img/banner-image-6.jpg",
    "first-impression-caption": "Banner Image 6",
    "first-impression-order": 6
  },

{
    "first-impression-image": "feature-img/banner-image-3.jpg",
    "first-impression-caption": "Banner Image 3",
    "first-impression-order": 7
  }
]